{
  "users": [
    {
      "id": 1,
      "name": "Agustin",
      "email": "appollonioagustin@gmail.com",
      "passWord": "12345",
      "baja": 1,
      "rutinas": [
        "Lorem ipsum dolor sit amet consectetur adipisicing elit. Voluptates, delectus reprehenderit. Sequi saepe numquam ab, velit possimus debitis.",
        "Lorem ipsum dolor sit amet consectetur adipisicing elit. Voluptates, delectus reprehenderit."
      ],
      "recetas": [
        "Lorem ipsum dolor sit amet consectetur adipisicing elit. Voluptates, delectus reprehenderit. Sequi saepe numquam ab, velit possimus debitis.",
        "Lorem ipsum dolor sit amet consectetur adipisicing elit. Voluptates, delectus reprehenderit."
      ]
    },
    {
      "id": 2,
      "name": "asdbasd",
      "lastname": "sidbalsd",
      "email": "appollonioagustin@dsd4.com",
      "passWord": "sagdblisd",
      "baja": 0,
      "rutinas": [],
      "recetas": []
    }
  ]
}